[{"name": "\u0414\u0438\u0430\u043b\u0435\u043a\u0442\u0438\u043a", "text": "", "img": null, "username": "dialectic_club", "message_id": "5794", "link": "https://t.me/s/dialectic_club/5794", "hash": null}, {"name": "\u041f\u0440\u043e\u0441\u0442\u044b\u0435 \u0447\u0438\u0441\u043b\u0430: \u043f\u043e\u043b\u0438\u0442\u044d\u043a\u043e\u043d\u043e\u043c\u0438\u044f \u043e\u043d\u043b\u0430\u0439\u043d", "text": "", "img": null, "username": "primenumbers2021", "message_id": "2194", "link": "https://t.me/s/primenumbers2021/2194", "hash": null}, {"name": "\u0414\u0438\u0430\u043b\u0435\u043a\u0442\u0438\u043a", "text": "", "img": null, "username": "dialectic_club", "message_id": "5793", "link": "https://t.me/s/dialectic_club/5793", "hash": null}, {"name": "\u0412\u044b\u0445\u043e\u0434 \u0415\u0441\u0442\u044c!", "text": "", "img": null, "username": "vihod_est", "message_id": "1166", "link": "https://t.me/s/vihod_est/1166", "hash": null}, {"name": "\u0410\u0413\u0418\u0422\u041f\u0420\u041e\u041f", "text": "", "img": null, "username": "Agitblog", "message_id": "21498", "link": "https://t.me/s/Agitblog/21498", "hash": null}, {"name": "\u0412\u0435\u0441\u0442\u043d\u0438\u043a \u0411\u0443\u0440\u0438 Originals", "text": "", "img": null, "username": "vestnikburioriginals", "message_id": "7067", "link": "https://t.me/s/vestnikburioriginals/7067", "hash": null}, {"name": "\u041f\u043e\u0431\u0435\u0434\u0438\u0442\u0435\u043b\u044c", "text": "", "img": null, "username": "pbdsu", "message_id": "12276", "link": "https://t.me/s/pbdsu/12276", "hash": null}, {"name": "Politeconomics", "text": "", "img": null, "username": "politeconomics", "message_id": "12107", "link": "https://t.me/s/politeconomics/12107", "hash": null}, {"name": "\u0410\u0413\u0418\u0422\u041f\u0420\u041e\u041f", "text": "", "img": null, "username": "Agitblog", "message_id": "21497", "link": "https://t.me/s/Agitblog/21497", "hash": null}, {"name": "\u041f\u043e\u0431\u0435\u0434\u0438\u0442\u0435\u043b\u044c", "text": "", "img": null, "username": "pbdsu", "message_id": "12275", "link": "https://t.me/s/pbdsu/12275", "hash": null}, {"name": "\u0410\u0413\u0418\u0422\u041f\u0420\u041e\u041f", "text": "", "img": null, "username": "Agitblog", "message_id": "21492", "link": "https://t.me/s/Agitblog/21492", "hash": null}, {"name": "\u041f\u043e\u0431\u0435\u0434\u0438\u0442\u0435\u043b\u044c", "text": "", "img": null, "username": "pbdsu", "message_id": "12274", "link": "https://t.me/s/pbdsu/12274", "hash": null}, {"name": "\u0420\u0430\u0431\u043a\u043e\u0440", "text": "", "img": null, "username": "rabkor", "message_id": "13946", "link": "https://t.me/s/rabkor/13946", "hash": null}, {"name": "\u0423 \u0416\u0443\u043a\u043e\u0432\u0430", "text": "", "img": null, "username": "uzhukova", "message_id": "5562", "link": "https://t.me/s/uzhukova/5562", "hash": null}, {"name": "\u0423 \u0416\u0443\u043a\u043e\u0432\u0430", "text": "", "img": null, "username": "uzhukova", "message_id": "5561", "link": "https://t.me/s/uzhukova/5561", "hash": null}, {"name": "\u0410\u0413\u0418\u0422\u041f\u0420\u041e\u041f", "text": "", "img": null, "username": "Agitblog", "message_id": "21491", "link": "https://t.me/s/Agitblog/21491", "hash": null}, {"name": "\u041f\u0440\u043e\u0441\u0442\u044b\u0435 \u0447\u0438\u0441\u043b\u0430: \u043f\u043e\u043b\u0438\u0442\u044d\u043a\u043e\u043d\u043e\u043c\u0438\u044f \u043e\u043d\u043b\u0430\u0439\u043d", "text": "", "img": null, "username": "primenumbers2021", "message_id": "2193", "link": "https://t.me/s/primenumbers2021/2193", "hash": null}, {"name": "\u0414\u0443\u043c\u0430\u0439 \u0441\u0430\u043c/\u0414\u0443\u043c\u0430\u0439 \u0441\u0435\u0439\u0447\u0430\u0441.", "text": "", "img": null, "username": "dumai_sam_i_sei4as", "message_id": "2158", "link": "https://t.me/s/dumai_sam_i_sei4as/2158", "hash": null}, {"name": "\u0421\u043e\u044e\u0437 \u043c\u0430\u0440\u043a\u0441\u0438\u0441\u0442\u043e\u0432", "text": "", "img": null, "username": "marx_union", "message_id": "5207", "link": "https://t.me/s/marx_union/5207", "hash": null}, {"name": "\u0414\u0438\u0430\u043b\u0435\u043a\u0442\u0438\u043a", "text": "", "img": null, "username": "dialectic_club", "message_id": "5792", "link": "https://t.me/s/dialectic_club/5792", "hash": null}, {"name": "\u0410\u0413\u0418\u0422\u041f\u0420\u041e\u041f", "text": "", "img": null, "username": "Agitblog", "message_id": "21490", "link": "https://t.me/s/Agitblog/21490", "hash": null}, {"name": "\u0420\u0443\u0434\u043e\u0439", "text": "", "img": null, "username": "ru_doy", "message_id": "3323", "link": "https://t.me/s/ru_doy/3323", "hash": null}, {"name": "\u0420\u0430\u0431\u043a\u043e\u0440", "text": "", "img": null, "username": "rabkor", "message_id": "13945", "link": "https://t.me/s/rabkor/13945", "hash": null}, {"name": "\u0420\u0443\u0434\u043e\u0439", "text": "", "img": null, "username": "ru_doy", "message_id": "3322", "link": "https://t.me/s/ru_doy/3322", "hash": null}, {"name": "\u0421\u043e\u0432\u0435\u0442\u0441\u043a\u0438\u0435 \u0443\u0447\u0435\u0431\u043d\u0438\u043a\u0438", "text": "", "img": null, "username": "sovuche", "message_id": "6433", "link": "https://t.me/s/sovuche/6433", "hash": null}, {"name": "\u0421\u043e\u0432\u0435\u0442\u0441\u043a\u0438\u0435 \u0443\u0447\u0435\u0431\u043d\u0438\u043a\u0438", "text": "", "img": null, "username": "sovuche", "message_id": "6432", "link": "https://t.me/s/sovuche/6432", "hash": null}, {"name": "Politeconomics", "text": "", "img": null, "username": "politeconomics", "message_id": "12106", "link": "https://t.me/s/politeconomics/12106", "hash": null}, {"name": "\u041f\u041b\u041e\u0425\u041e\u0419 \u0421\u0418\u0413\u041d\u0410\u041b", "text": "", "img": null, "username": "plohoysignal", "message_id": "432", "link": "https://t.me/s/plohoysignal/432", "hash": null}, {"name": "\u0414\u0438\u0430\u043b\u0435\u043a\u0442\u0438\u043a", "text": "", "img": null, "username": "dialectic_club", "message_id": "5791", "link": "https://t.me/s/dialectic_club/5791", "hash": null}, {"name": "\u0420\u0443\u0434\u043e\u0439", "text": "", "img": null, "username": "ru_doy", "message_id": "3321", "link": "https://t.me/s/ru_doy/3321", "hash": null}, {"name": "\u041f\u041b\u041e\u0425\u041e\u0419 \u0421\u0418\u0413\u041d\u0410\u041b", "text": "", "img": null, "username": "plohoysignal", "message_id": "431", "link": "https://t.me/s/plohoysignal/431", "hash": null}, {"name": "\u0412\u0435\u0441\u0442\u043d\u0438\u043a \u0411\u0443\u0440\u0438 Originals", "text": "", "img": null, "username": "vestnikburioriginals", "message_id": "7066", "link": "https://t.me/s/vestnikburioriginals/7066", "hash": null}, {"name": "\u0420\u0430\u0431\u043a\u043e\u0440", "text": "", "img": null, "username": "rabkor", "message_id": "13944", "link": "https://t.me/s/rabkor/13944", "hash": null}, {"name": "\u0420\u0430\u0431\u043a\u043e\u0440", "text": "", "img": null, "username": "rabkor", "message_id": "13943", "link": "https://t.me/s/rabkor/13943", "hash": null}, {"name": "\u0414\u0443\u043c\u0430\u0439 \u0441\u0430\u043c/\u0414\u0443\u043c\u0430\u0439 \u0441\u0435\u0439\u0447\u0430\u0441.", "text": "", "img": null, "username": "dumai_sam_i_sei4as", "message_id": "2157", "link": "https://t.me/s/dumai_sam_i_sei4as/2157", "hash": null}, {"name": "\u041f\u043e\u0431\u0435\u0434\u0438\u0442\u0435\u043b\u044c", "text": "", "img": null, "username": "pbdsu", "message_id": "12273", "link": "https://t.me/s/pbdsu/12273", "hash": null}, {"name": "\u0414\u0438\u0430\u043b\u0435\u043a\u0442\u0438\u043a", "text": "", "img": null, "username": "dialectic_club", "message_id": "5790", "link": "https://t.me/s/dialectic_club/5790", "hash": null}, {"name": "\u041a\u0443\u043b\u044c\u0442\u043f\u0440\u043e\u0441\u0432\u0435\u0442", "text": "", "img": null, "username": "kultprosvet1917", "message_id": "118", "link": "https://t.me/s/kultprosvet1917/118", "hash": null}, {"name": "\u0423 \u0416\u0443\u043a\u043e\u0432\u0430", "text": "", "img": null, "username": "uzhukova", "message_id": "5560", "link": "https://t.me/s/uzhukova/5560", "hash": null}, {"name": "\u0412\u044b\u0445\u043e\u0434 \u0415\u0441\u0442\u044c!", "text": "", "img": null, "username": "vihod_est", "message_id": "1165", "link": "https://t.me/s/vihod_est/1165", "hash": null}, {"name": "\u0412\u044b\u0445\u043e\u0434 \u0415\u0441\u0442\u044c!", "text": "", "img": null, "username": "vihod_est", "message_id": "1164", "link": "https://t.me/s/vihod_est/1164", "hash": null}, {"name": "\u0420\u0430\u0431\u043a\u043e\u0440", "text": "", "img": null, "username": "rabkor", "message_id": "13942", "link": "https://t.me/s/rabkor/13942", "hash": null}, {"name": "\u0410\u0413\u0418\u0422\u041f\u0420\u041e\u041f", "text": "", "img": null, "username": "Agitblog", "message_id": "21489", "link": "https://t.me/s/Agitblog/21489", "hash": null}, {"name": "\u0414\u0438\u0430\u043b\u0435\u043a\u0442\u0438\u043a", "text": "", "img": null, "username": "dialectic_club", "message_id": "5789", "link": "https://t.me/s/dialectic_club/5789", "hash": null}, {"name": "\u0410\u0413\u0418\u0422\u041f\u0420\u041e\u041f", "text": "", "img": null, "username": "Agitblog", "message_id": "21488", "link": "https://t.me/s/Agitblog/21488", "hash": null}, {"name": "\u0410\u0413\u0418\u0422\u041f\u0420\u041e\u041f", "text": "", "img": null, "username": "Agitblog", "message_id": "21487", "link": "https://t.me/s/Agitblog/21487", "hash": null}, {"name": "\u0421\u043e\u0432\u0435\u0442\u0441\u043a\u0438\u0435 \u0443\u0447\u0435\u0431\u043d\u0438\u043a\u0438", "text": "", "img": null, "username": "sovuche", "message_id": "6431", "link": "https://t.me/s/sovuche/6431", "hash": null}, {"name": "\u0420\u0430\u0431\u043a\u043e\u0440", "text": "", "img": null, "username": "rabkor", "message_id": "13941", "link": "https://t.me/s/rabkor/13941", "hash": null}, {"name": "Politeconomics", "text": "", "img": null, "username": "politeconomics", "message_id": "12105", "link": "https://t.me/s/politeconomics/12105", "hash": null}, {"name": "\u041f\u043e\u0431\u0435\u0434\u0438\u0442\u0435\u043b\u044c", "text": "", "img": null, "username": "pbdsu", "message_id": "12272", "link": "https://t.me/s/pbdsu/12272", "hash": null}, {"name": "\u0420\u0430\u0431\u043a\u043e\u0440", "text": "", "img": null, "username": "rabkor", "message_id": "13940", "link": "https://t.me/s/rabkor/13940", "hash": null}, {"name": "\u0421\u043e\u0432\u0435\u0442\u0441\u043a\u0438\u0435 \u0443\u0447\u0435\u0431\u043d\u0438\u043a\u0438", "text": "", "img": null, "username": "sovuche", "message_id": "6426", "link": "https://t.me/s/sovuche/6426", "hash": null}, {"name": "\u0414\u0443\u043c\u0430\u0439 \u0441\u0430\u043c/\u0414\u0443\u043c\u0430\u0439 \u0441\u0435\u0439\u0447\u0430\u0441.", "text": "", "img": null, "username": "dumai_sam_i_sei4as", "message_id": "2156", "link": "https://t.me/s/dumai_sam_i_sei4as/2156", "hash": null}, {"name": "\u041f\u043e\u0431\u0435\u0434\u0438\u0442\u0435\u043b\u044c", "text": "", "img": null, "username": "pbdsu", "message_id": "12271", "link": "https://t.me/s/pbdsu/12271", "hash": null}, {"name": "\u0410\u0413\u0418\u0422\u041f\u0420\u041e\u041f", "text": "", "img": null, "username": "Agitblog", "message_id": "21483", "link": "https://t.me/s/Agitblog/21483", "hash": null}, {"name": "\u041f\u043e\u0431\u0435\u0434\u0438\u0442\u0435\u043b\u044c", "text": "", "img": null, "username": "pbdsu", "message_id": "12270", "link": "https://t.me/s/pbdsu/12270", "hash": null}, {"name": "\u041f\u043e\u0431\u0435\u0434\u0438\u0442\u0435\u043b\u044c", "text": "", "img": null, "username": "pbdsu", "message_id": "12269", "link": "https://t.me/s/pbdsu/12269", "hash": null}, {"name": "M0therHacker backplace", "text": "", "img": null, "username": "motherhckr", "message_id": "1295", "link": "https://t.me/s/motherhckr/1295", "hash": null}, {"name": "\u041f\u0440\u043e\u0441\u0442\u044b\u0435 \u0447\u0438\u0441\u043b\u0430: \u043f\u043e\u043b\u0438\u0442\u044d\u043a\u043e\u043d\u043e\u043c\u0438\u044f \u043e\u043d\u043b\u0430\u0439\u043d", "text": "", "img": null, "username": "primenumbers2021", "message_id": "2192", "link": "https://t.me/s/primenumbers2021/2192", "hash": null}, {"name": "\u0421\u043e\u044e\u0437 \u043c\u0430\u0440\u043a\u0441\u0438\u0441\u0442\u043e\u0432", "text": "", "img": null, "username": "marx_union", "message_id": "5205", "link": "https://t.me/s/marx_union/5205", "hash": null}, {"name": "\u0414\u0438\u0430\u043b\u0435\u043a\u0442\u0438\u043a", "text": "", "img": null, "username": "dialectic_club", "message_id": "5788", "link": "https://t.me/s/dialectic_club/5788", "hash": null}, {"name": "\u0420\u0430\u0431\u043a\u043e\u0440", "text": "", "img": null, "username": "rabkor", "message_id": "13939", "link": "https://t.me/s/rabkor/13939", "hash": null}, {"name": "\u0414\u0438\u0430\u043b\u0435\u043a\u0442\u0438\u043a", "text": "", "img": null, "username": "dialectic_club", "message_id": "5787", "link": "https://t.me/s/dialectic_club/5787", "hash": null}, {"name": "\u041e\u0440\u0433\u0430\u043d\u0438\u0437\u0430\u0446\u0438\u044f \u043a\u043e\u043c\u043c\u0443\u043d\u0438\u0441\u0442\u043e\u0432-\u0438\u043d\u0442\u0435\u0440\u043d\u0430\u0446\u0438\u043e\u043d\u0430\u043b\u0438\u0441\u0442\u043e\u0432 (\u041e\u041a\u0418)", "text": "", "img": null, "username": "okintern", "message_id": "3111", "link": "https://t.me/s/okintern/3111", "hash": null}, {"name": "\u0423 \u0416\u0443\u043a\u043e\u0432\u0430", "text": "", "img": null, "username": "uzhukova", "message_id": "5559", "link": "https://t.me/s/uzhukova/5559", "hash": null}, {"name": "\u0423 \u0416\u0443\u043a\u043e\u0432\u0430", "text": "", "img": null, "username": "uzhukova", "message_id": "5558", "link": "https://t.me/s/uzhukova/5558", "hash": null}, {"name": "\u041e\u0440\u0433\u0430\u043d\u0438\u0437\u0430\u0446\u0438\u044f \u043a\u043e\u043c\u043c\u0443\u043d\u0438\u0441\u0442\u043e\u0432-\u0438\u043d\u0442\u0435\u0440\u043d\u0430\u0446\u0438\u043e\u043d\u0430\u043b\u0438\u0441\u0442\u043e\u0432 (\u041e\u041a\u0418)", "text": "", "img": null, "username": "okintern", "message_id": "3110", "link": "https://t.me/s/okintern/3110", "hash": null}, {"name": "\u0410\u0413\u0418\u0422\u041f\u0420\u041e\u041f", "text": "", "img": null, "username": "Agitblog", "message_id": "21482", "link": "https://t.me/s/Agitblog/21482", "hash": null}, {"name": "\u041e\u0440\u0433\u0430\u043d\u0438\u0437\u0430\u0446\u0438\u044f \u043a\u043e\u043c\u043c\u0443\u043d\u0438\u0441\u0442\u043e\u0432-\u0438\u043d\u0442\u0435\u0440\u043d\u0430\u0446\u0438\u043e\u043d\u0430\u043b\u0438\u0441\u0442\u043e\u0432 (\u041e\u041a\u0418)", "text": "", "img": null, "username": "okintern", "message_id": "3109", "link": "https://t.me/s/okintern/3109", "hash": null}, {"name": "\u0420\u0430\u0431\u043a\u043e\u0440", "text": "", "img": null, "username": "rabkor", "message_id": "13938", "link": "https://t.me/s/rabkor/13938", "hash": null}, {"name": "\u0414\u0443\u043c\u0430\u0439 \u0441\u0430\u043c/\u0414\u0443\u043c\u0430\u0439 \u0441\u0435\u0439\u0447\u0430\u0441.", "text": "", "img": null, "username": "dumai_sam_i_sei4as", "message_id": "2155", "link": "https://t.me/s/dumai_sam_i_sei4as/2155", "hash": null}, {"name": "\u0421\u043e\u044e\u0437 \u043c\u0430\u0440\u043a\u0441\u0438\u0441\u0442\u043e\u0432", "text": "", "img": null, "username": "marx_union", "message_id": "5204", "link": "https://t.me/s/marx_union/5204", "hash": null}, {"name": "\u041e\u0440\u0433\u0430\u043d\u0438\u0437\u0430\u0446\u0438\u044f \u043a\u043e\u043c\u043c\u0443\u043d\u0438\u0441\u0442\u043e\u0432-\u0438\u043d\u0442\u0435\u0440\u043d\u0430\u0446\u0438\u043e\u043d\u0430\u043b\u0438\u0441\u0442\u043e\u0432 (\u041e\u041a\u0418)", "text": "", "img": null, "username": "okintern", "message_id": "3108", "link": "https://t.me/s/okintern/3108", "hash": null}, {"name": "\u0420\u0430\u0431\u043a\u043e\u0440", "text": "", "img": null, "username": "rabkor", "message_id": "13937", "link": "https://t.me/s/rabkor/13937", "hash": null}, {"name": "\u0421\u043e\u0432\u0435\u0442\u0441\u043a\u0438\u0435 \u0443\u0447\u0435\u0431\u043d\u0438\u043a\u0438", "text": "", "img": null, "username": "sovuche", "message_id": "6425", "link": "https://t.me/s/sovuche/6425", "hash": null}, {"name": "\u0421\u043e\u0432\u0435\u0442\u0441\u043a\u0438\u0435 \u0443\u0447\u0435\u0431\u043d\u0438\u043a\u0438", "text": "", "img": null, "username": "sovuche", "message_id": "6424", "link": "https://t.me/s/sovuche/6424", "hash": null}, {"name": "\u0420\u0430\u0431\u043a\u043e\u0440", "text": "", "img": null, "username": "rabkor", "message_id": "13936", "link": "https://t.me/s/rabkor/13936", "hash": null}, {"name": "\u041e\u0440\u0433\u0430\u043d\u0438\u0437\u0430\u0446\u0438\u044f \u043a\u043e\u043c\u043c\u0443\u043d\u0438\u0441\u0442\u043e\u0432-\u0438\u043d\u0442\u0435\u0440\u043d\u0430\u0446\u0438\u043e\u043d\u0430\u043b\u0438\u0441\u0442\u043e\u0432 (\u041e\u041a\u0418)", "text": "", "img": null, "username": "okintern", "message_id": "3107", "link": "https://t.me/s/okintern/3107", "hash": null}, {"name": "\u0420\u0430\u0431\u043a\u043e\u0440", "text": "", "img": null, "username": "rabkor", "message_id": "13935", "link": "https://t.me/s/rabkor/13935", "hash": null}, {"name": "\u0414\u0438\u0430\u043b\u0435\u043a\u0442\u0438\u043a", "text": "", "img": null, "username": "dialectic_club", "message_id": "5786", "link": "https://t.me/s/dialectic_club/5786", "hash": null}, {"name": "\u0420\u0430\u0431\u043a\u043e\u0440", "text": "", "img": null, "username": "rabkor", "message_id": "13934", "link": "https://t.me/s/rabkor/13934", "hash": null}, {"name": "\u0420\u0443\u0434\u043e\u0439", "text": "", "img": null, "username": "ru_doy", "message_id": "3320", "link": "https://t.me/s/ru_doy/3320", "hash": null}, {"name": "\u0420\u0430\u0431\u043a\u043e\u0440", "text": "", "img": null, "username": "rabkor", "message_id": "13933", "link": "https://t.me/s/rabkor/13933", "hash": null}, {"name": "\u0414\u0443\u043c\u0430\u0439 \u0441\u0430\u043c/\u0414\u0443\u043c\u0430\u0439 \u0441\u0435\u0439\u0447\u0430\u0441.", "text": "", "img": null, "username": "dumai_sam_i_sei4as", "message_id": "2154", "link": "https://t.me/s/dumai_sam_i_sei4as/2154", "hash": null}, {"name": "\u0414\u0438\u0430\u043b\u0435\u043a\u0442\u0438\u043a", "text": "", "img": null, "username": "dialectic_club", "message_id": "5785", "link": "https://t.me/s/dialectic_club/5785", "hash": null}, {"name": "\u0420\u0443\u0434\u043e\u0439", "text": "", "img": null, "username": "ru_doy", "message_id": "3319", "link": "https://t.me/s/ru_doy/3319", "hash": null}, {"name": "\u0420\u0430\u0431\u043a\u043e\u0440", "text": "", "img": null, "username": "rabkor", "message_id": "13932", "link": "https://t.me/s/rabkor/13932", "hash": null}, {"name": "\u0421\u043e\u0432\u0435\u0442\u0441\u043a\u0438\u0435 \u0443\u0447\u0435\u0431\u043d\u0438\u043a\u0438", "text": "", "img": null, "username": "sovuche", "message_id": "6423", "link": "https://t.me/s/sovuche/6423", "hash": null}, {"name": "\u0421\u043e\u0432\u0435\u0442\u0441\u043a\u0438\u0435 \u0443\u0447\u0435\u0431\u043d\u0438\u043a\u0438", "text": "", "img": null, "username": "sovuche", "message_id": "6422", "link": "https://t.me/s/sovuche/6422", "hash": null}, {"name": "\u0420\u0430\u0431\u043a\u043e\u0440", "text": "", "img": null, "username": "rabkor", "message_id": "13931", "link": "https://t.me/s/rabkor/13931", "hash": null}, {"name": "\u0414\u0438\u0430\u043b\u0435\u043a\u0442\u0438\u043a", "text": "", "img": null, "username": "dialectic_club", "message_id": "5784", "link": "https://t.me/s/dialectic_club/5784", "hash": null}, {"name": "Politeconomics", "text": "", "img": null, "username": "politeconomics", "message_id": "12104", "link": "https://t.me/s/politeconomics/12104", "hash": null}, {"name": "\u0414\u0443\u043c\u0430\u0439 \u0441\u0430\u043c/\u0414\u0443\u043c\u0430\u0439 \u0441\u0435\u0439\u0447\u0430\u0441.", "text": "", "img": null, "username": "dumai_sam_i_sei4as", "message_id": "2153", "link": "https://t.me/s/dumai_sam_i_sei4as/2153", "hash": null}, {"name": "\u0420\u0430\u0431\u043a\u043e\u0440", "text": "", "img": null, "username": "rabkor", "message_id": "13930", "link": "https://t.me/s/rabkor/13930", "hash": null}, {"name": "\u0414\u0438\u0430\u043b\u0435\u043a\u0442\u0438\u043a", "text": "", "img": null, "username": "dialectic_club", "message_id": "5783", "link": "https://t.me/s/dialectic_club/5783", "hash": null}, {"name": "\u0420\u0430\u0431\u043a\u043e\u0440", "text": "", "img": null, "username": "rabkor", "message_id": "13929", "link": "https://t.me/s/rabkor/13929", "hash": null}, {"name": "\u0414\u0443\u043c\u0430\u0439 \u0441\u0430\u043c/\u0414\u0443\u043c\u0430\u0439 \u0441\u0435\u0439\u0447\u0430\u0441.", "text": "", "img": null, "username": "dumai_sam_i_sei4as", "message_id": "2152", "link": "https://t.me/s/dumai_sam_i_sei4as/2152", "hash": null}, {"name": "\u041f\u041b\u041e\u0425\u041e\u0419 \u0421\u0418\u0413\u041d\u0410\u041b", "text": "", "img": null, "username": "plohoysignal", "message_id": "430", "link": "https://t.me/s/plohoysignal/430", "hash": null}, {"name": "\u0414\u0438\u0430\u043b\u0435\u043a\u0442\u0438\u043a", "text": "", "img": null, "username": "dialectic_club", "message_id": "5782", "link": "https://t.me/s/dialectic_club/5782", "hash": null}, {"name": "\u0412\u044b\u0445\u043e\u0434 \u0415\u0441\u0442\u044c!", "text": "", "img": null, "username": "vihod_est", "message_id": "1163", "link": "https://t.me/s/vihod_est/1163", "hash": null}, {"name": "\u0420\u0430\u0431\u043a\u043e\u0440", "text": "", "img": null, "username": "rabkor", "message_id": "13928", "link": "https://t.me/s/rabkor/13928", "hash": null}, {"name": "\u0421\u043e\u0432\u0435\u0442\u0441\u043a\u0438\u0435 \u0443\u0447\u0435\u0431\u043d\u0438\u043a\u0438", "text": "", "img": null, "username": "sovuche", "message_id": "6421", "link": "https://t.me/s/sovuche/6421", "hash": null}, {"name": "\u0421\u043e\u0432\u0435\u0442\u0441\u043a\u0438\u0435 \u0443\u0447\u0435\u0431\u043d\u0438\u043a\u0438", "text": "", "img": null, "username": "sovuche", "message_id": "6420", "link": "https://t.me/s/sovuche/6420", "hash": null}, {"name": "\u0414\u0443\u043c\u0430\u0439 \u0441\u0430\u043c/\u0414\u0443\u043c\u0430\u0439 \u0441\u0435\u0439\u0447\u0430\u0441.", "text": "", "img": null, "username": "dumai_sam_i_sei4as", "message_id": "2151", "link": "https://t.me/s/dumai_sam_i_sei4as/2151", "hash": null}, {"name": "M0therHacker backplace", "text": "", "img": null, "username": "motherhckr", "message_id": "1291", "link": "https://t.me/s/motherhckr/1291", "hash": null}, {"name": "\u0420\u0430\u0431\u043a\u043e\u0440", "text": "", "img": null, "username": "rabkor", "message_id": "13925", "link": "https://t.me/s/rabkor/13925", "hash": null}, {"name": "\u0420\u0443\u0434\u043e\u0439", "text": "", "img": null, "username": "ru_doy", "message_id": "3318", "link": "https://t.me/s/ru_doy/3318", "hash": null}, {"name": "\u041f\u043e\u0431\u0435\u0434\u0438\u0442\u0435\u043b\u044c", "text": "", "img": null, "username": "pbdsu", "message_id": "12266", "link": "https://t.me/s/pbdsu/12266", "hash": null}, {"name": "\u0420\u0430\u0431\u043a\u043e\u0440", "text": "", "img": null, "username": "rabkor", "message_id": "13924", "link": "https://t.me/s/rabkor/13924", "hash": null}, {"name": "\u0420\u0430\u0431\u043a\u043e\u0440", "text": "", "img": null, "username": "rabkor", "message_id": "13923", "link": "https://t.me/s/rabkor/13923", "hash": null}, {"name": "\u0420\u0430\u0431\u043a\u043e\u0440", "text": "", "img": null, "username": "rabkor", "message_id": "13922", "link": "https://t.me/s/rabkor/13922", "hash": null}, {"name": "M0therHacker backplace", "text": "", "img": null, "username": "motherhckr", "message_id": "1290", "link": "https://t.me/s/motherhckr/1290", "hash": null}, {"name": "\u0420\u0430\u0431\u043a\u043e\u0440", "text": "", "img": null, "username": "rabkor", "message_id": "13917", "link": "https://t.me/s/rabkor/13917", "hash": null}, {"name": "\u0414\u0438\u0430\u043b\u0435\u043a\u0442\u0438\u043a", "text": "", "img": null, "username": "dialectic_club", "message_id": "5781", "link": "https://t.me/s/dialectic_club/5781", "hash": null}, {"name": "\u0420\u0430\u0431\u043a\u043e\u0440", "text": "", "img": null, "username": "rabkor", "message_id": "13916", "link": "https://t.me/s/rabkor/13916", "hash": null}, {"name": "\u0414\u0438\u0430\u043b\u0435\u043a\u0442\u0438\u043a", "text": "", "img": null, "username": "dialectic_club", "message_id": "5780", "link": "https://t.me/s/dialectic_club/5780", "hash": null}, {"name": "\u0421\u043e\u0432\u0435\u0442\u0441\u043a\u0438\u0435 \u0443\u0447\u0435\u0431\u043d\u0438\u043a\u0438", "text": "", "img": null, "username": "sovuche", "message_id": "6419", "link": "https://t.me/s/sovuche/6419", "hash": null}, {"name": "\u0421\u043e\u0432\u0435\u0442\u0441\u043a\u0438\u0435 \u0443\u0447\u0435\u0431\u043d\u0438\u043a\u0438", "text": "", "img": null, "username": "sovuche", "message_id": "6418", "link": "https://t.me/s/sovuche/6418", "hash": null}, {"name": "\u0420\u0430\u0431\u043a\u043e\u0440", "text": "", "img": null, "username": "rabkor", "message_id": "13915", "link": "https://t.me/s/rabkor/13915", "hash": null}, {"name": "\u0421\u043e\u044e\u0437 \u043c\u0430\u0440\u043a\u0441\u0438\u0441\u0442\u043e\u0432", "text": "", "img": null, "username": "marx_union", "message_id": "5200", "link": "https://t.me/s/marx_union/5200", "hash": null}]